deepaclive/__init__.py
deepaclive/command_line.py
deepaclive/receiver.py
deepaclive/refilter.py
deepaclive/sender.py
deepaclive/sftp_client.py
deepaclive/tests.py
deepaclive-0.3.2.dist-info/LICENSE
deepaclive-0.3.2.dist-info/METADATA
deepaclive-0.3.2.dist-info/WHEEL
deepaclive-0.3.2.dist-info/entry_points.txt
deepaclive-0.3.2.dist-info/top_level.txt
deepaclive-0.3.2.dist-info/RECORD
